pyvideothumbnailer/__init__.py
pyvideothumbnailer/_videothumnailer.py
pyvideothumbnailer/videothumbnailer.py
pyvideothumbnailer-2.2.0.dist-info/licenses/LICENSE
pyvideothumbnailer-2.2.0.dist-info/METADATA
pyvideothumbnailer-2.2.0.dist-info/WHEEL
pyvideothumbnailer-2.2.0.dist-info/entry_points.txt
pyvideothumbnailer-2.2.0.dist-info/top_level.txt
pyvideothumbnailer-2.2.0.dist-info/RECORD
