Metadata-Version: 2.4
Name: pyvideothumbnailer
Version: 2.2.0
Summary: A command line tool for creating video preview thumbnails images.
Author-email: Harald Hetzner <57875126+hhtznr@users.noreply.github.com>
Project-URL: Homepage, https://github.com/hhtznr/pyvideothumbnailer
Project-URL: Bug Tracker, https://github.com/hhtznr/pyvideothumbnailer/issues
Classifier: Programming Language :: Python :: 3
Classifier: License :: OSI Approved :: BSD License
Classifier: Operating System :: OS Independent
Requires-Python: >=3.7
License-File: LICENSE
Requires-Dist: av>=9.0.0
Requires-Dist: pymediainfo>=4.3
Requires-Dist: Pillow>=9.2.0
Dynamic: license-file
